purchase/__init__.py
purchase/admin.py
purchase/apps.py
purchase/controllers/__init__.py
purchase/controllers/log_controller.py
purchase/controllers/process_controller_abc.py
purchase/controllers/purchase_controller.py
purchase/controllers/subscription_controller.py
purchase/exceptions/__init__.py
purchase/exceptions/custom_status.py
purchase/loggers/__init__.py
purchase/loggers/adjust_logger.py
purchase/loggers/apps_flyer_logger.py
purchase/loggers/facebook_logger.py
purchase/migrations/0001_initial.py
purchase/migrations/0002_auto_20210920_1019.py
purchase/migrations/0003_auto_20220215_0611.py
purchase/migrations/0004_subscription.py
purchase/migrations/0005_alter_subscription_user.py
purchase/migrations/0006_alter_subscription__is_active.py
purchase/migrations/0007_purchase_user.py
purchase/migrations/0008_auto_20220801_0606.py
purchase/migrations/0009_auto_20220801_0845.py
purchase/migrations/__init__.py
purchase/models/__init__.py
purchase/models/adjust.py
purchase/models/adjust_log.py
purchase/models/apps_flyer.py
purchase/models/choices.py
purchase/models/config.py
purchase/models/facebook.py
purchase/models/google.py
purchase/models/log.py
purchase/models/purchase.py
purchase/models/subscription.py
purchase/serializers/__init__.py
purchase/serializers/config_response_serializer.py
purchase/serializers/request_serialzier.py
purchase/serializers/response_serializer.py
purchase/serializers/subscription_response_serializer.py
purchase/signals/__init__.py
purchase/signals/purchase_completed_signal.py
purchase/signals/subscription_completed_signal.py
purchase/strings/__init__.py
purchase/strings/errors.py
purchase/strings/log_levels.py
purchase/strings/loggers.py
purchase/strings/verifiers.py
purchase/templates/__init__.py
purchase/templates/google_json_load_form.html
purchase/urls.py
purchase/utils.py
purchase/verifiers/__init__.py
purchase/verifiers/apple_verifier.py
purchase/verifiers/google_verifier.py
purchase/views/__init__.py
purchase/views/log_config.py
django_purchase_core-0.3.63.dist-info/WHEEL
django_purchase_core-0.3.63.dist-info/METADATA
django_purchase_core-0.3.63.dist-info/RECORD
