Metadata-Version: 2.1
Name: django-purchase-core
Version: 0.3.63
Summary: A reusable Django app for creating, logging and verifying purchases.
Home-page: https://github.com/boy-scouts/game-core-purchase
License: MIT
Author: Qmobi
Author-email: info@qmobi.com
Requires-Python: >=3.8,<4.0
Classifier: License :: OSI Approved :: MIT License
Classifier: Programming Language :: Python :: 3
Classifier: Programming Language :: Python :: 3.10
Classifier: Programming Language :: Python :: 3.8
Classifier: Programming Language :: Python :: 3.9
Requires-Dist: Django (>=4.0.1,<5.0.0)
Requires-Dist: Pygments (>=2.10.0,<3.0.0)
Requires-Dist: django-admin-rangefilter (>=0.8.1,<0.9.0)
Requires-Dist: django-filter (>=2.4.0,<3.0.0)
Requires-Dist: djangorestframework (>=3.12.4,<4.0.0)
Requires-Dist: drf-yasg (>=1.21.3,<2.0.0)
Requires-Dist: google (>=3.0.0,<4.0.0)
Requires-Dist: google-api-python-client (>=2.21.0,<3.0.0)
Requires-Dist: google-auth (>=2.1.0,<3.0.0)
Requires-Dist: google-auth-oauthlib (>=0.4.6,<0.5.0)
Requires-Dist: requests (>=2.26.0,<3.0.0)
Project-URL: Repository, https://github.com/boy-scouts/game-core-purchase
